setup.py
xiot.py
xiotshell.py
xiot.egg-info/PKG-INFO
xiot.egg-info/SOURCES.txt
xiot.egg-info/dependency_links.txt
xiot.egg-info/requires.txt
xiot.egg-info/top_level.txt