Metadata-Version: 1.0
Name: xiot
Version: 1.4.5
Summary: A lib for xiot.
Home-page: https://github.com/sintrb/xiot
Author: Robin
Author-email: sintrb@gmail.com
License: Apache License 2.0
Keywords: xiot
Platform: UNKNOWN
